insidellm/__init__.py
insidellm/client.py
insidellm/config.py
insidellm/context_manager.py
insidellm/decorators.py
insidellm/exceptions.py
insidellm/langchain_integration.py
insidellm/local_logger.py
insidellm/models.py
insidellm/queue_manager.py
insidellm/utils.py
insidellm-1.0.0.dist-info/licenses/LICENSE
insidellm-1.0.0.dist-info/METADATA
insidellm-1.0.0.dist-info/WHEEL
insidellm-1.0.0.dist-info/top_level.txt
insidellm-1.0.0.dist-info/RECORD
